rosbags/convert/__init__.py
rosbags/convert/__main__.py
rosbags/convert/cli.py
rosbags/convert/commands.py
rosbags/convert/converter.py
rosbags/convert/declinate.py
rosbags/convert/py.typed
rosbags/highlevel/__init__.py
rosbags/highlevel/anyreader.py
rosbags/highlevel/py.typed
rosbags/interfaces/__init__.py
rosbags/interfaces/py.typed
rosbags/interfaces/typing.py
rosbags/rosbag1/__init__.py
rosbags/rosbag1/py.typed
rosbags/rosbag1/reader.py
rosbags/rosbag1/writer.py
rosbags/rosbag2/__init__.py
rosbags/rosbag2/errors.py
rosbags/rosbag2/metadata.py
rosbags/rosbag2/py.typed
rosbags/rosbag2/reader.py
rosbags/rosbag2/storage_mcap.py
rosbags/rosbag2/storage_sqlite3.py
rosbags/rosbag2/writer.py
rosbags/serde/__init__.py
rosbags/serde/cdr.py
rosbags/serde/deprecated.py
rosbags/serde/errors.py
rosbags/serde/primitives.py
rosbags/serde/py.typed
rosbags/serde/ros1.py
rosbags/serde/utils.py
rosbags/typesys/__init__.py
rosbags/typesys/__main__.py
rosbags/typesys/base.py
rosbags/typesys/codegen.py
rosbags/typesys/deprecated.py
rosbags/typesys/idl.py
rosbags/typesys/msg.py
rosbags/typesys/peg.py
rosbags/typesys/py.typed
rosbags/typesys/store.py
rosbags/typesys/types.py
rosbags/typesys/stores/__init__.py
rosbags/typesys/stores/empty.py
rosbags/typesys/stores/latest.py
rosbags/typesys/stores/ros1_noetic.py
rosbags/typesys/stores/ros2_dashing.py
rosbags/typesys/stores/ros2_eloquent.py
rosbags/typesys/stores/ros2_foxy.py
rosbags/typesys/stores/ros2_galactic.py
rosbags/typesys/stores/ros2_humble.py
rosbags/typesys/stores/ros2_iron.py
rosbags/typesys/stores/ros2_jazzy.py
sixriver_rosbags-0.0.4.dist-info/LICENSE.txt
sixriver_rosbags-0.0.4.dist-info/METADATA
sixriver_rosbags-0.0.4.dist-info/WHEEL
sixriver_rosbags-0.0.4.dist-info/entry_points.txt
sixriver_rosbags-0.0.4.dist-info/top_level.txt
sixriver_rosbags-0.0.4.dist-info/RECORD
