Metadata-Version: 2.1
Name: sixriver_rosbags
Version: 0.0.4
Summary: Pure Python library to read, modify, convert, and write rosbag files.
Author-email: Ternaris <team@ternaris.com>
License: Apache-2.0
Project-URL: Homepage, https://gitlab.com/ternaris/rosbags
Project-URL: Documentation, https://ternaris.gitlab.io/rosbags
Project-URL: Source, https://gitlab.com/ternaris/rosbags
Project-URL: Issues, https://gitlab.com/ternaris/rosbags/issues
Project-URL: Changelog, https://gitlab.com/ternaris/rosbags/-/blob/master/CHANGES.rst
Keywords: cdr,conversion,deserialization,idl,mcap,message,msg,reader,ros,ros2,rosbag,rosbag2,serialization,writer
Classifier: Development Status :: 4 - Beta
Classifier: License :: OSI Approved :: Apache Software License
Classifier: Programming Language :: Python
Classifier: Programming Language :: Python :: 3 :: Only
Classifier: Programming Language :: Python :: 3.10
Classifier: Programming Language :: Python :: 3.11
Classifier: Programming Language :: Python :: 3.12
Classifier: Topic :: Scientific/Engineering
Classifier: Typing :: Typed
Requires-Python: >=3.10
License-File: LICENSE.txt
Requires-Dist: lz4
Requires-Dist: numpy
Requires-Dist: ruamel.yaml
Requires-Dist: typing-extensions
Requires-Dist: zstandard
Provides-Extra: dev
Requires-Dist: declinate ; extra == 'dev'
Requires-Dist: mypy ; extra == 'dev'
Requires-Dist: pytest ; extra == 'dev'
Requires-Dist: pytest-cov ; extra == 'dev'
Requires-Dist: reuse ; extra == 'dev'
Requires-Dist: ruff ; extra == 'dev'
Requires-Dist: sphinx ; extra == 'dev'
Requires-Dist: sphinx-autodoc-typehints ; extra == 'dev'
Requires-Dist: sphinx-rtd-theme ; extra == 'dev'
